{
  "users": [{
    "id": 2,
    "username": "MrBimble",
    "uploaded_avatar_id": 29,
    "avatar_template": "/user_avatar/talk.polygonalweave.com/mrbimble/{size}/29_1.png"
  }, {
    "id": 1,
    "username": "Rewfus",
    "uploaded_avatar_id": 69,
    "avatar_template": "/user_avatar/talk.polygonalweave.com/rewfus/{size}/69_1.png"
  }, {
    "id": 4,
    "username": "katet",
    "uploaded_avatar_id": 94,
    "avatar_template": "/user_avatar/talk.polygonalweave.com/katet/{size}/94_1.png"
  }, {
    "id": 7,
    "username": "Jango",
    "uploaded_avatar_id": 149,
    "avatar_template": "/user_avatar/talk.polygonalweave.com/jango/{size}/149_1.png"
  }, {
    "id": 37,
    "username": "CrazyThang01",
    "uploaded_avatar_id": 126,
    "avatar_template": "/user_avatar/talk.polygonalweave.com/crazythang01/{size}/126_1.png"
  }, {
    "id": 13,
    "username": "DarthSmurfX",
    "uploaded_avatar_id": 73,
    "avatar_template": "/user_avatar/talk.polygonalweave.com/darthsmurfx/{size}/73_1.png"
  }, {
    "id": 17,
    "username": "ChristopheLeFou",
    "uploaded_avatar_id": 76,
    "avatar_template": "/user_avatar/talk.polygonalweave.com/christophelefou/{size}/76_1.png"
  }, {
    "id": 8,
    "username": "Threctory",
    "uploaded_avatar_id": 48,
    "avatar_template": "/user_avatar/talk.polygonalweave.com/threctory/{size}/48_1.png"
  }, {
    "id": 15,
    "username": "blackzipper",
    "uploaded_avatar_id": 57,
    "avatar_template": "/user_avatar/talk.polygonalweave.com/blackzipper/{size}/57_1.png"
  }, {
    "id": 14,
    "username": "CodSteaks",
    "uploaded_avatar_id": 56,
    "avatar_template": "/user_avatar/talk.polygonalweave.com/codsteaks/{size}/56_1.png"
  }, {
    "id": 43,
    "username": "Dillon_J_Mahonay",
    "uploaded_avatar_id": 140,
    "avatar_template": "/user_avatar/talk.polygonalweave.com/dillon_j_mahonay/{size}/140_1.png"
  }],
  "topic_list": {
    "can_create_topic": true,
    "more_topics_url": "/c/games/l/latest?category_id=5&page=1",
    "draft": null,
    "draft_key": "new_topic",
    "draft_sequence": 153,
    "per_page": 30,
    "topics": [{
      "id": 361,
      "title": "Law Breakers",
      "fancy_title": "Law Breakers",
      "slug": "law-breakers",
      "posts_count": 5,
      "reply_count": 1,
      "highest_post_number": 5,
      "image_url": "http://static.giantbomb.com/uploads/scale_small/8/82063/2654720-rcjm76j2.jpeg",
      "created_at": "2015-08-24T17:40:44.469Z",
      "last_posted_at": "2015-08-26T16:15:15.273Z",
      "bumped": true,
      "bumped_at": "2015-08-26T16:15:15.273Z",
      "unseen": false,
      "last_read_post_number": 5,
      "unread": 0,
      "new_posts": 0,
      "pinned": false,
      "unpinned": null,
      "visible": true,
      "closed": false,
      "archived": false,
      "notification_level": 2,
      "bookmarked": false,
      "liked": false,
      "views": 15,
      "like_count": 0,
      "has_summary": false,
      "archetype": "regular",
      "last_poster_username": "Rewfus",
      "category_id": 5,
      "pinned_globally": false,
      "tags": null,
      "posters": [{
        "extras": null,
        "description": "Original Poster",
        "user_id": 2
      }, {
        "extras": "latest",
        "description": "Most Recent Poster, Frequent Poster",
        "user_id": 1
      }]
    }, {
      "id": 180,
      "title": "Rocket League",
      "fancy_title": "Rocket League",
      "slug": "rocket-league",
      "posts_count": 74,
      "reply_count": 29,
      "highest_post_number": 101,
      "image_url": "http://static.giantbomb.com/uploads/scale_small/1/12096/1728492-pitchrender_flatten_final.jpg",
      "created_at": "2015-05-18T15:35:34.119Z",
      "last_posted_at": "2015-08-26T15:59:31.466Z",
      "bumped": true,
      "bumped_at": "2015-08-26T15:59:31.466Z",
      "unseen": false,
      "last_read_post_number": 101,
      "unread": 0,
      "new_posts": 0,
      "pinned": false,
      "unpinned": null,
      "visible": true,
      "closed": false,
      "archived": false,
      "notification_level": 3,
      "bookmarked": false,
      "liked": true,
      "views": 400,
      "like_count": 22,
      "has_summary": true,
      "archetype": "regular",
      "last_poster_username": "MrBimble",
      "category_id": 5,
      "pinned_globally": false,
      "tags": null,
      "posters": [{
        "extras": null,
        "description": "Original Poster",
        "user_id": 1
      }, {
        "extras": null,
        "description": "Frequent Poster",
        "user_id": 4
      }, {
        "extras": null,
        "description": "Frequent Poster",
        "user_id": 7
      }, {
        "extras": null,
        "description": "Frequent Poster",
        "user_id": 37
      }, {
        "extras": "latest",
        "description": "Most Recent Poster",
        "user_id": 2
      }]
    }, {
      "id": 366,
      "title": "Diablo III: Ultimate Evil Edition",
      "fancy_title": "Diablo III: Ultimate Evil Edition",
      "slug": "diablo-iii-ultimate-evil-edition",
      "posts_count": 1,
      "reply_count": 0,
      "highest_post_number": 1,
      "image_url": "http://static.giantbomb.com/uploads/scale_small/0/3699/2676025-diablo+iii+-+ultimate+evil+edition+v4.jpg",
      "created_at": "2015-08-26T15:46:11.683Z",
      "last_posted_at": "2015-08-26T15:46:11.968Z",
      "bumped": true,
      "bumped_at": "2015-08-26T15:46:11.968Z",
      "unseen": false,
      "last_read_post_number": 1,
      "unread": 0,
      "new_posts": 0,
      "pinned": false,
      "unpinned": null,
      "visible": true,
      "closed": false,
      "archived": false,
      "notification_level": 3,
      "bookmarked": false,
      "liked": false,
      "views": 3,
      "like_count": 0,
      "has_summary": false,
      "archetype": "regular",
      "last_poster_username": "Rewfus",
      "category_id": 5,
      "pinned_globally": false,
      "tags": null,
      "posters": [{
        "extras": "latest single",
        "description": "Original Poster, Most Recent Poster",
        "user_id": 1
      }]
    }, {
      "id": 82,
      "title": "Driveclub",
      "fancy_title": "Driveclub",
      "slug": "driveclub",
      "posts_count": 29,
      "reply_count": 7,
      "highest_post_number": 29,
      "image_url": "http://static.giantbomb.com/uploads/scale_small/8/82063/2560905-driveclub.jpg",
      "created_at": "2015-04-27T18:52:24.164Z",
      "last_posted_at": "2015-08-26T14:45:47.806Z",
      "bumped": true,
      "bumped_at": "2015-08-26T14:45:47.806Z",
      "unseen": false,
      "last_read_post_number": 29,
      "unread": 0,
      "new_posts": 0,
      "pinned": false,
      "unpinned": null,
      "visible": true,
      "closed": false,
      "archived": false,
      "notification_level": 2,
      "bookmarked": false,
      "liked": true,
      "views": 185,
      "like_count": 3,
      "has_summary": false,
      "archetype": "regular",
      "last_poster_username": "DarthSmurfX",
      "category_id": 5,
      "pinned_globally": false,
      "tags": null,
      "posters": [{
        "extras": "latest",
        "description": "Original Poster, Most Recent Poster",
        "user_id": 13
      }, {
        "extras": null,
        "description": "Frequent Poster",
        "user_id": 4
      }, {
        "extras": null,
        "description": "Frequent Poster",
        "user_id": 17
      }, {
        "extras": null,
        "description": "Frequent Poster",
        "user_id": 1
      }]
    }, {
      "id": 23,
      "title": "Destiny",
      "fancy_title": "Destiny",
      "slug": "destiny",
      "posts_count": 196,
      "reply_count": 52,
      "highest_post_number": 196,
      "image_url": "http://static.giantbomb.com/uploads/scale_small/0/3699/2669576-destiny+v2.jpg",
      "created_at": "2015-04-01T17:13:18.782Z",
      "last_posted_at": "2015-08-26T14:34:48.456Z",
      "bumped": true,
      "bumped_at": "2015-08-26T14:34:48.456Z",
      "unseen": false,
      "last_read_post_number": 196,
      "unread": 0,
      "new_posts": 0,
      "pinned": false,
      "unpinned": null,
      "visible": true,
      "closed": false,
      "archived": false,
      "notification_level": 2,
      "bookmarked": false,
      "liked": true,
      "views": 785,
      "like_count": 23,
      "has_summary": true,
      "archetype": "regular",
      "last_poster_username": "DarthSmurfX",
      "category_id": 5,
      "pinned_globally": false,
      "tags": null,
      "posters": [{
        "extras": null,
        "description": "Original Poster",
        "user_id": 2
      }, {
        "extras": null,
        "description": "Frequent Poster",
        "user_id": 8
      }, {
        "extras": null,
        "description": "Frequent Poster",
        "user_id": 4
      }, {
        "extras": null,
        "description": "Frequent Poster",
        "user_id": 15
      }, {
        "extras": "latest",
        "description": "Most Recent Poster",
        "user_id": 13
      }]
    }, {
      "id": 95,
      "title": "Journey",
      "fancy_title": "Journey",
      "slug": "journey",
      "posts_count": 7,
      "reply_count": 0,
      "highest_post_number": 7,
      "image_url": "http://static.giantbomb.com/uploads/scale_small/4/44183/2388618-2172218_journey_detailcropped.png",
      "created_at": "2015-04-28T16:14:23.172Z",
      "last_posted_at": "2015-08-24T15:51:05.548Z",
      "bumped": true,
      "bumped_at": "2015-08-26T14:33:09.028Z",
      "unseen": false,
      "last_read_post_number": 7,
      "unread": 0,
      "new_posts": 0,
      "pinned": false,
      "unpinned": null,
      "visible": true,
      "closed": false,
      "archived": false,
      "notification_level": 2,
      "bookmarked": false,
      "liked": false,
      "views": 81,
      "like_count": 0,
      "has_summary": false,
      "archetype": "regular",
      "last_poster_username": "DarthSmurfX",
      "category_id": 5,
      "pinned_globally": false,
      "tags": null,
      "posters": [{
        "extras": "latest",
        "description": "Original Poster, Most Recent Poster",
        "user_id": 13
      }, {
        "extras": null,
        "description": "Frequent Poster",
        "user_id": 14
      }, {
        "extras": null,
        "description": "Frequent Poster",
        "user_id": 1
      }]
    }, {
      "id": 156,
      "title": "Tom Clancy's The Division",
      "fancy_title": "Tom Clancy&rsquo;s The Division",
      "slug": "tom-clancys-the-division",
      "posts_count": 8,
      "reply_count": 4,
      "highest_post_number": 8,
      "image_url": "http://static.giantbomb.com/uploads/scale_small/9/95676/2643697-91pvshkpjfl._sl1500_+-+copy.jpg",
      "created_at": "2015-05-12T18:21:19.820Z",
      "last_posted_at": "2015-08-26T13:06:41.151Z",
      "bumped": true,
      "bumped_at": "2015-08-26T13:06:41.151Z",
      "unseen": false,
      "last_read_post_number": 8,
      "unread": 0,
      "new_posts": 0,
      "pinned": false,
      "unpinned": null,
      "visible": true,
      "closed": false,
      "archived": false,
      "notification_level": 3,
      "bookmarked": false,
      "liked": false,
      "views": 51,
      "like_count": 0,
      "has_summary": false,
      "archetype": "regular",
      "last_poster_username": "Rewfus",
      "category_id": 5,
      "pinned_globally": false,
      "tags": null,
      "posters": [{
        "extras": "latest",
        "description": "Original Poster, Most Recent Poster",
        "user_id": 1
      }, {
        "extras": null,
        "description": "Frequent Poster",
        "user_id": 8
      }, {
        "extras": null,
        "description": "Frequent Poster",
        "user_id": 2
      }, {
        "extras": null,
        "description": "Frequent Poster",
        "user_id": 4
      }, {
        "extras": null,
        "description": "Frequent Poster",
        "user_id": 14
      }]
    }, {
      "id": 279,
      "title": "WWE 2K16 - Here Comes the Shame",
      "fancy_title": "WWE 2K16 - Here Comes the Shame",
      "slug": "wwe-2k16-here-comes-the-shame",
      "posts_count": 9,
      "reply_count": 2,
      "highest_post_number": 9,
      "image_url": "http://static.giantbomb.com/uploads/scale_small/0/39/2763969-2ksmkt_wwe2k16_ps4_fob_noamarayedges.jpg",
      "created_at": "2015-07-27T16:18:10.150Z",
      "last_posted_at": "2015-08-25T20:53:22.090Z",
      "bumped": true,
      "bumped_at": "2015-08-25T20:53:22.090Z",
      "unseen": false,
      "last_read_post_number": 9,
      "unread": 0,
      "new_posts": 0,
      "pinned": false,
      "unpinned": null,
      "visible": true,
      "closed": false,
      "archived": false,
      "notification_level": 2,
      "bookmarked": false,
      "liked": false,
      "views": 74,
      "like_count": 0,
      "has_summary": false,
      "archetype": "regular",
      "last_poster_username": "DarthSmurfX",
      "category_id": 5,
      "pinned_globally": false,
      "tags": null,
      "posters": [{
        "extras": "latest",
        "description": "Original Poster, Most Recent Poster",
        "user_id": 13
      }, {
        "extras": null,
        "description": "Frequent Poster",
        "user_id": 1
      }, {
        "extras": null,
        "description": "Frequent Poster",
        "user_id": 43
      }, {
        "extras": null,
        "description": "Frequent Poster",
        "user_id": 8
      }]
    }, {
      "id": 363,
      "title": "Trailers",
      "fancy_title": "Trailers",
      "slug": "trailers",
      "posts_count": 2,
      "reply_count": 0,
      "highest_post_number": 2,
      "image_url": null,
      "created_at": "2015-08-24T18:19:29.675Z",
      "last_posted_at": "2015-08-25T20:22:43.570Z",
      "bumped": true,
      "bumped_at": "2015-08-25T20:22:43.570Z",
      "unseen": false,
      "last_read_post_number": 2,
      "unread": 0,
      "new_posts": 0,
      "pinned": false,
      "unpinned": null,
      "visible": true,
      "closed": false,
      "archived": false,
      "notification_level": 3,
      "bookmarked": false,
      "liked": false,
      "views": 4,
      "like_count": 0,
      "has_summary": false,
      "archetype": "regular",
      "last_poster_username": "Rewfus",
      "category_id": 22,
      "pinned_globally": false,
      "tags": null,
      "posters": [{
        "extras": "latest single",
        "description": "Original Poster, Most Recent Poster",
        "user_id": 1
      }]
    }, {
      "id": 365,
      "title": "Game Links",
      "fancy_title": "Game Links",
      "slug": "game-links",
      "posts_count": 4,
      "reply_count": 0,
      "highest_post_number": 4,
      "image_url": null,
      "created_at": "2015-08-24T18:36:51.089Z",
      "last_posted_at": "2015-08-25T20:21:10.215Z",
      "bumped": true,
      "bumped_at": "2015-08-25T20:21:10.215Z",
      "unseen": false,
      "last_read_post_number": 4,
      "unread": 0,
      "new_posts": 0,
      "pinned": false,
      "unpinned": null,
      "visible": true,
      "closed": false,
      "archived": false,
      "notification_level": 3,
      "bookmarked": false,
      "liked": false,
      "views": 4,
      "like_count": 0,
      "has_summary": false,
      "archetype": "regular",
      "last_poster_username": "Rewfus",
      "category_id": 23,
      "pinned_globally": false,
      "tags": null,
      "posters": [{
        "extras": "latest single",
        "description": "Original Poster, Most Recent Poster",
        "user_id": 1
      }]
    }, {
      "id": 236,
      "title": "Horizon Zero Dawn",
      "fancy_title": "Horizon Zero Dawn",
      "slug": "horizon-zero-dawn",
      "posts_count": 10,
      "reply_count": 1,
      "highest_post_number": 10,
      "image_url": "http://static.giantbomb.com/uploads/scale_small/8/81005/2758869-7570785732-2015-.jpg",
      "created_at": "2015-06-16T13:08:38.040Z",
      "last_posted_at": "2015-08-25T16:24:25.908Z",
      "bumped": true,
      "bumped_at": "2015-08-25T16:24:25.908Z",
      "unseen": false,
      "last_read_post_number": 10,
      "unread": 0,
      "new_posts": 0,
      "pinned": false,
      "unpinned": null,
      "visible": true,
      "closed": false,
      "archived": false,
      "notification_level": 3,
      "bookmarked": false,
      "liked": true,
      "views": 102,
      "like_count": 2,
      "has_summary": false,
      "archetype": "regular",
      "last_poster_username": "DarthSmurfX",
      "category_id": 5,
      "pinned_globally": false,
      "tags": null,
      "posters": [{
        "extras": null,
        "description": "Original Poster",
        "user_id": 1
      }, {
        "extras": null,
        "description": "Frequent Poster",
        "user_id": 17
      }, {
        "extras": "latest",
        "description": "Most Recent Poster",
        "user_id": 13
      }]
    }, {
      "id": 120,
      "title": "Rock Band 4",
      "fancy_title": "Rock Band 4",
      "slug": "rock-band-4",
      "posts_count": 26,
      "reply_count": 11,
      "highest_post_number": 26,
      "image_url": "http://assets2.ignimgs.com/2015/05/03/sidebandaltjpg-72e1ec_610w.jpg",
      "created_at": "2015-05-04T16:34:28.615Z",
      "last_posted_at": "2015-08-25T14:59:19.925Z",
      "bumped": true,
      "bumped_at": "2015-08-25T14:59:19.925Z",
      "unseen": false,
      "last_read_post_number": 26,
      "unread": 0,
      "new_posts": 0,
      "pinned": false,
      "unpinned": null,
      "visible": true,
      "closed": false,
      "archived": false,
      "notification_level": 2,
      "bookmarked": false,
      "liked": true,
      "views": 162,
      "like_count": 6,
      "has_summary": false,
      "archetype": "regular",
      "last_poster_username": "DarthSmurfX",
      "category_id": 5,
      "pinned_globally": false,
      "tags": null,
      "posters": [{
        "extras": "latest",
        "description": "Original Poster, Most Recent Poster",
        "user_id": 13
      }, {
        "extras": null,
        "description": "Frequent Poster",
        "user_id": 1
      }, {
        "extras": null,
        "description": "Frequent Poster",
        "user_id": 8
      }, {
        "extras": null,
        "description": "Frequent Poster",
        "user_id": 17
      }, {
        "extras": null,
        "description": "Frequent Poster",
        "user_id": 2
      }]
    }, {
      "id": 360,
      "title": "Everybody's Gone to Rapture",
      "fancy_title": "Everybody&rsquo;s Gone to Rapture",
      "slug": "everybodys-gone-to-rapture",
      "posts_count": 1,
      "reply_count": 0,
      "highest_post_number": 1,
      "image_url": null,
      "created_at": "2015-08-24T17:36:12.773Z",
      "last_posted_at": "2015-08-24T17:36:13.559Z",
      "bumped": true,
      "bumped_at": "2015-08-24T17:36:13.559Z",
      "unseen": false,
      "last_read_post_number": 1,
      "unread": 0,
      "new_posts": 0,
      "pinned": false,
      "unpinned": null,
      "visible": true,
      "closed": false,
      "archived": false,
      "notification_level": 3,
      "bookmarked": false,
      "liked": false,
      "views": 2,
      "like_count": 0,
      "has_summary": false,
      "archetype": "regular",
      "last_poster_username": "Rewfus",
      "category_id": 21,
      "pinned_globally": false,
      "tags": null,
      "posters": [{
        "extras": "latest single",
        "description": "Original Poster, Most Recent Poster",
        "user_id": 1
      }]
    }, {
      "id": 194,
      "title": "Until Dawn",
      "fancy_title": "Until Dawn",
      "slug": "until-dawn",
      "posts_count": 2,
      "reply_count": 0,
      "highest_post_number": 2,
      "image_url": "http://static.giantbomb.com/uploads/scale_small/8/82063/2292958-untildawn.jpg",
      "created_at": "2015-05-26T15:19:00.848Z",
      "last_posted_at": "2015-08-24T17:18:57.178Z",
      "bumped": true,
      "bumped_at": "2015-08-24T17:18:57.178Z",
      "unseen": false,
      "last_read_post_number": 2,
      "unread": 0,
      "new_posts": 0,
      "pinned": false,
      "unpinned": null,
      "visible": true,
      "closed": false,
      "archived": false,
      "notification_level": 3,
      "bookmarked": false,
      "liked": false,
      "views": 40,
      "like_count": 0,
      "has_summary": false,
      "archetype": "regular",
      "last_poster_username": "Rewfus",
      "category_id": 5,
      "pinned_globally": false,
      "tags": null,
      "posters": [{
        "extras": "latest single",
        "description": "Original Poster, Most Recent Poster",
        "user_id": 1
      }]
    }, {
      "id": 358,
      "title": "Metal Gear Solid V: The Phantom Pain",
      "fancy_title": "Metal Gear Solid V: The Phantom Pain",
      "slug": "metal-gear-solid-v-the-phantom-pain",
      "posts_count": 1,
      "reply_count": 0,
      "highest_post_number": 1,
      "image_url": "http://static.giantbomb.com/uploads/scale_small/8/82063/2731604-mgsvclean.jpg",
      "created_at": "2015-08-24T14:23:48.725Z",
      "last_posted_at": "2015-08-24T14:23:48.929Z",
      "bumped": true,
      "bumped_at": "2015-08-24T14:23:48.929Z",
      "unseen": false,
      "last_read_post_number": 1,
      "unread": 0,
      "new_posts": 0,
      "pinned": false,
      "unpinned": null,
      "visible": true,
      "closed": false,
      "archived": false,
      "notification_level": 3,
      "bookmarked": false,
      "liked": false,
      "views": 7,
      "like_count": 0,
      "has_summary": false,
      "archetype": "regular",
      "last_poster_username": "Rewfus",
      "category_id": 5,
      "pinned_globally": false,
      "tags": null,
      "posters": [{
        "extras": "latest single",
        "description": "Original Poster, Most Recent Poster",
        "user_id": 1
      }]
    }, {
      "id": 357,
      "title": "Star Fox Zero",
      "fancy_title": "Star Fox Zero",
      "slug": "star-fox-zero",
      "posts_count": 2,
      "reply_count": 0,
      "highest_post_number": 2,
      "image_url": "http://static.giantbomb.com/uploads/scale_small/8/82063/2760808-sf0.jpg",
      "created_at": "2015-08-24T13:53:02.226Z",
      "last_posted_at": "2015-08-24T14:15:34.883Z",
      "bumped": true,
      "bumped_at": "2015-08-24T14:15:34.883Z",
      "unseen": false,
      "last_read_post_number": 2,
      "unread": 0,
      "new_posts": 0,
      "pinned": false,
      "unpinned": null,
      "visible": true,
      "closed": false,
      "archived": false,
      "notification_level": 1,
      "bookmarked": false,
      "liked": false,
      "views": 8,
      "like_count": 0,
      "has_summary": false,
      "archetype": "regular",
      "last_poster_username": "CrazyThang01",
      "category_id": 5,
      "pinned_globally": false,
      "tags": null,
      "posters": [{
        "extras": null,
        "description": "Original Poster",
        "user_id": 2
      }, {
        "extras": "latest",
        "description": "Most Recent Poster",
        "user_id": 37
      }]
    }, {
      "id": 74,
      "title": "Call of Duty: Black Ops III",
      "fancy_title": "Call of Duty: Black Ops III",
      "slug": "call-of-duty-black-ops-iii",
      "posts_count": 15,
      "reply_count": 2,
      "highest_post_number": 15,
      "image_url": "http://static.giantbomb.com/uploads/scale_small/18/187968/2745029-rsz_image2.jpg",
      "created_at": "2015-04-26T22:27:19.516Z",
      "last_posted_at": "2015-08-24T13:09:30.799Z",
      "bumped": true,
      "bumped_at": "2015-08-24T13:09:30.799Z",
      "unseen": false,
      "last_read_post_number": 15,
      "unread": 0,
      "new_posts": 0,
      "pinned": false,
      "unpinned": null,
      "visible": true,
      "closed": false,
      "archived": false,
      "notification_level": 3,
      "bookmarked": false,
      "liked": true,
      "views": 120,
      "like_count": 1,
      "has_summary": false,
      "archetype": "regular",
      "last_poster_username": "Rewfus",
      "category_id": 5,
      "pinned_globally": false,
      "tags": null,
      "posters": [{
        "extras": "latest",
        "description": "Original Poster, Most Recent Poster",
        "user_id": 1
      }, {
        "extras": null,
        "description": "Frequent Poster",
        "user_id": 8
      }, {
        "extras": null,
        "description": "Frequent Poster",
        "user_id": 2
      }]
    }, {
      "id": 196,
      "title": "Everybody's Gone to the Rapture",
      "fancy_title": "Everybody&rsquo;s Gone to the Rapture",
      "slug": "everybodys-gone-to-the-rapture",
      "posts_count": 15,
      "reply_count": 2,
      "highest_post_number": 15,
      "image_url": "http://static.giantbomb.com/uploads/scale_small/0/4344/2146327-rapture1.jpg",
      "created_at": "2015-05-28T15:00:59.106Z",
      "last_posted_at": "2015-08-20T18:36:16.791Z",
      "bumped": true,
      "bumped_at": "2015-08-20T18:36:16.791Z",
      "unseen": false,
      "last_read_post_number": 15,
      "unread": 0,
      "new_posts": 0,
      "pinned": false,
      "unpinned": null,
      "visible": true,
      "closed": false,
      "archived": false,
      "notification_level": 2,
      "bookmarked": false,
      "liked": true,
      "views": 105,
      "like_count": 3,
      "has_summary": false,
      "archetype": "regular",
      "last_poster_username": "MrBimble",
      "category_id": 5,
      "pinned_globally": false,
      "tags": null,
      "posters": [{
        "extras": null,
        "description": "Original Poster",
        "user_id": 13
      }, {
        "extras": null,
        "description": "Frequent Poster",
        "user_id": 4
      }, {
        "extras": null,
        "description": "Frequent Poster",
        "user_id": 1
      }, {
        "extras": "latest",
        "description": "Most Recent Poster",
        "user_id": 2
      }]
    }, {
      "id": 243,
      "title": "Halo 5: Guardians",
      "fancy_title": "Halo 5: Guardians",
      "slug": "halo-5-guardians",
      "posts_count": 4,
      "reply_count": 1,
      "highest_post_number": 4,
      "image_url": "http://static.giantbomb.com/uploads/scale_small/8/84290/2745464-halo5_keyart_vert_final.jpg",
      "created_at": "2015-06-18T14:33:17.675Z",
      "last_posted_at": "2015-08-20T15:39:13.132Z",
      "bumped": true,
      "bumped_at": "2015-08-20T15:39:13.132Z",
      "unseen": false,
      "last_read_post_number": 4,
      "unread": 0,
      "new_posts": 0,
      "pinned": false,
      "unpinned": null,
      "visible": true,
      "closed": false,
      "archived": false,
      "notification_level": 3,
      "bookmarked": false,
      "liked": false,
      "views": 60,
      "like_count": 0,
      "has_summary": false,
      "archetype": "regular",
      "last_poster_username": "DarthSmurfX",
      "category_id": 5,
      "pinned_globally": false,
      "tags": null,
      "posters": [{
        "extras": null,
        "description": "Original Poster",
        "user_id": 1
      }, {
        "extras": null,
        "description": "Frequent Poster",
        "user_id": 2
      }, {
        "extras": "latest",
        "description": "Most Recent Poster",
        "user_id": 13
      }]
    }, {
      "id": 224,
      "title": "Toy Soldiers: War Chest",
      "fancy_title": "Toy Soldiers: War Chest",
      "slug": "toy-soldiers-war-chest",
      "posts_count": 16,
      "reply_count": 4,
      "highest_post_number": 16,
      "image_url": "https://ubistatic9-a.akamaihd.net/ubicomstatic/en-US/global/search-thumbnail/toys_search_Mobile_171170.jpg",
      "created_at": "2015-06-10T18:24:34.712Z",
      "last_posted_at": "2015-08-20T15:06:18.167Z",
      "bumped": true,
      "bumped_at": "2015-08-20T15:06:18.167Z",
      "unseen": false,
      "last_read_post_number": 16,
      "unread": 0,
      "new_posts": 0,
      "pinned": false,
      "unpinned": null,
      "visible": true,
      "closed": false,
      "archived": false,
      "notification_level": 3,
      "bookmarked": false,
      "liked": false,
      "views": 134,
      "like_count": 2,
      "has_summary": false,
      "archetype": "regular",
      "last_poster_username": "DarthSmurfX",
      "category_id": 5,
      "pinned_globally": false,
      "tags": null,
      "posters": [{
        "extras": null,
        "description": "Original Poster",
        "user_id": 1
      }, {
        "extras": null,
        "description": "Frequent Poster",
        "user_id": 2
      }, {
        "extras": null,
        "description": "Frequent Poster",
        "user_id": 7
      }, {
        "extras": "latest",
        "description": "Most Recent Poster",
        "user_id": 13
      }]
    }, {
      "id": 328,
      "title": "RIGS: Mechanized Combat League",
      "fancy_title": "RIGS: Mechanized Combat League",
      "slug": "rigs-mechanized-combat-league",
      "posts_count": 4,
      "reply_count": 0,
      "highest_post_number": 4,
      "image_url": "http://static.giantbomb.com/uploads/scale_small/0/1992/2758944-screen+shot+2015-06-16+at+2.26.55+am.jpg",
      "created_at": "2015-08-19T20:48:42.953Z",
      "last_posted_at": "2015-08-19T22:44:03.464Z",
      "bumped": true,
      "bumped_at": "2015-08-19T22:44:03.464Z",
      "unseen": false,
      "last_read_post_number": 4,
      "unread": 0,
      "new_posts": 0,
      "pinned": false,
      "unpinned": null,
      "visible": true,
      "closed": false,
      "archived": false,
      "notification_level": 2,
      "bookmarked": false,
      "liked": false,
      "views": 26,
      "like_count": 1,
      "has_summary": false,
      "archetype": "regular",
      "last_poster_username": "Jango",
      "category_id": 5,
      "pinned_globally": false,
      "tags": null,
      "posters": [{
        "extras": null,
        "description": "Original Poster",
        "user_id": 13
      }, {
        "extras": null,
        "description": "Frequent Poster",
        "user_id": 1
      }, {
        "extras": "latest",
        "description": "Most Recent Poster",
        "user_id": 7
      }]
    }, {
      "id": 168,
      "title": "Tom Clancy's Rainbow Six: Siege",
      "fancy_title": "Tom Clancy&rsquo;s Rainbow Six: Siege",
      "slug": "tom-clancys-rainbow-six-siege",
      "posts_count": 4,
      "reply_count": 0,
      "highest_post_number": 4,
      "image_url": "http://static.giantbomb.com/uploads/scale_small/18/187968/2739110-rsz_811ju-locbl_sl1500_.jpg",
      "created_at": "2015-05-14T16:25:30.802Z",
      "last_posted_at": "2015-08-18T17:09:22.936Z",
      "bumped": true,
      "bumped_at": "2015-08-18T17:09:22.936Z",
      "unseen": false,
      "last_read_post_number": 4,
      "unread": 0,
      "new_posts": 0,
      "pinned": false,
      "unpinned": null,
      "visible": true,
      "closed": false,
      "archived": false,
      "notification_level": 2,
      "bookmarked": false,
      "liked": false,
      "views": 47,
      "like_count": 0,
      "has_summary": false,
      "archetype": "regular",
      "last_poster_username": "Rewfus",
      "category_id": 5,
      "pinned_globally": false,
      "tags": null,
      "posters": [{
        "extras": null,
        "description": "Original Poster",
        "user_id": 2
      }, {
        "extras": "latest",
        "description": "Most Recent Poster",
        "user_id": 1
      }]
    }, {
      "id": 320,
      "title": "Volume",
      "fancy_title": "Volume",
      "slug": "volume",
      "posts_count": 1,
      "reply_count": 0,
      "highest_post_number": 1,
      "image_url": "http://static.giantbomb.com/uploads/scale_small/1/14741/2528711-volume.png",
      "created_at": "2015-08-18T12:58:19.914Z",
      "last_posted_at": "2015-08-18T12:58:20.404Z",
      "bumped": true,
      "bumped_at": "2015-08-18T12:58:20.404Z",
      "unseen": false,
      "last_read_post_number": 1,
      "unread": 0,
      "new_posts": 0,
      "pinned": false,
      "unpinned": null,
      "visible": true,
      "closed": false,
      "archived": false,
      "notification_level": 3,
      "bookmarked": false,
      "liked": false,
      "views": 15,
      "like_count": 0,
      "has_summary": false,
      "archetype": "regular",
      "last_poster_username": "Rewfus",
      "category_id": 5,
      "pinned_globally": false,
      "tags": null,
      "posters": [{
        "extras": "latest single",
        "description": "Original Poster, Most Recent Poster",
        "user_id": 1
      }]
    }, {
      "id": 294,
      "title": "Gears of War",
      "fancy_title": "Gears of War",
      "slug": "gears-of-war",
      "posts_count": 5,
      "reply_count": 1,
      "highest_post_number": 5,
      "image_url": "http://static.giantbomb.com/uploads/scale_small/8/87790/1970470-box_gow.png",
      "created_at": "2015-08-03T14:29:09.956Z",
      "last_posted_at": "2015-08-17T19:57:28.129Z",
      "bumped": true,
      "bumped_at": "2015-08-17T19:57:28.129Z",
      "unseen": false,
      "last_read_post_number": 5,
      "unread": 0,
      "new_posts": 0,
      "pinned": false,
      "unpinned": null,
      "visible": true,
      "closed": false,
      "archived": false,
      "notification_level": 3,
      "bookmarked": false,
      "liked": false,
      "views": 51,
      "like_count": 0,
      "has_summary": false,
      "archetype": "regular",
      "last_poster_username": "Rewfus",
      "category_id": 5,
      "pinned_globally": false,
      "tags": null,
      "posters": [{
        "extras": "latest",
        "description": "Original Poster, Most Recent Poster",
        "user_id": 1
      }, {
        "extras": null,
        "description": "Frequent Poster",
        "user_id": 2
      }, {
        "extras": null,
        "description": "Frequent Poster",
        "user_id": 17
      }, {
        "extras": null,
        "description": "Frequent Poster",
        "user_id": 8
      }]
    }, {
      "id": 159,
      "title": "Uncharted 4: A Thief's End",
      "fancy_title": "Uncharted 4: A Thief&rsquo;s End",
      "slug": "uncharted-4-a-thiefs-end",
      "posts_count": 24,
      "reply_count": 3,
      "highest_post_number": 24,
      "image_url": "http://static.giantbomb.com/uploads/scale_small/9/95676/2644892-u4.jpg",
      "created_at": "2015-05-13T14:39:29.486Z",
      "last_posted_at": "2015-08-17T18:46:53.618Z",
      "bumped": true,
      "bumped_at": "2015-08-17T18:46:53.618Z",
      "unseen": false,
      "last_read_post_number": 24,
      "unread": 0,
      "new_posts": 0,
      "pinned": false,
      "unpinned": null,
      "visible": true,
      "closed": false,
      "archived": false,
      "notification_level": 2,
      "bookmarked": false,
      "liked": true,
      "views": 142,
      "like_count": 6,
      "has_summary": false,
      "archetype": "regular",
      "last_poster_username": "Threctory",
      "category_id": 5,
      "pinned_globally": false,
      "tags": null,
      "posters": [{
        "extras": null,
        "description": "Original Poster",
        "user_id": 13
      }, {
        "extras": null,
        "description": "Frequent Poster",
        "user_id": 2
      }, {
        "extras": null,
        "description": "Frequent Poster",
        "user_id": 15
      }, {
        "extras": null,
        "description": "Frequent Poster",
        "user_id": 17
      }, {
        "extras": "latest",
        "description": "Most Recent Poster",
        "user_id": 8
      }]
    }, {
      "id": 200,
      "title": "Kickstarter Pile: The Thread",
      "fancy_title": "Kickstarter Pile: The Thread",
      "slug": "kickstarter-pile-the-thread",
      "posts_count": 9,
      "reply_count": 3,
      "highest_post_number": 9,
      "image_url": "/uploads/default/optimized/3/b/3b6417bcd6444fb8cd138d36903d4871d8a0619e_300x300.png",
      "created_at": "2015-05-28T17:59:33.070Z",
      "last_posted_at": "2015-08-17T18:42:26.132Z",
      "bumped": true,
      "bumped_at": "2015-08-17T18:42:26.132Z",
      "unseen": false,
      "last_read_post_number": 9,
      "unread": 0,
      "new_posts": 0,
      "pinned": false,
      "unpinned": null,
      "visible": true,
      "closed": false,
      "archived": false,
      "notification_level": 2,
      "bookmarked": false,
      "liked": true,
      "views": 93,
      "like_count": 1,
      "has_summary": false,
      "archetype": "regular",
      "last_poster_username": "Threctory",
      "category_id": 5,
      "pinned_globally": false,
      "tags": null,
      "posters": [{
        "extras": null,
        "description": "Original Poster",
        "user_id": 17
      }, {
        "extras": null,
        "description": "Frequent Poster",
        "user_id": 1
      }, {
        "extras": "latest",
        "description": "Most Recent Poster",
        "user_id": 8
      }]
    }, {
      "id": 39,
      "title": "Star Wars: Battlefront",
      "fancy_title": "Star Wars: Battlefront",
      "slug": "star-wars-battlefront",
      "posts_count": 93,
      "reply_count": 19,
      "highest_post_number": 95,
      "image_url": "http://static.giantbomb.com/uploads/scale_small/18/187968/2743161-5356.jpg",
      "created_at": "2015-04-17T17:43:12.140Z",
      "last_posted_at": "2015-08-17T18:40:48.722Z",
      "bumped": true,
      "bumped_at": "2015-08-17T18:40:48.722Z",
      "unseen": false,
      "last_read_post_number": 95,
      "unread": 0,
      "new_posts": 0,
      "pinned": false,
      "unpinned": null,
      "visible": true,
      "closed": false,
      "archived": false,
      "notification_level": 2,
      "bookmarked": false,
      "liked": true,
      "views": 484,
      "like_count": 7,
      "has_summary": true,
      "archetype": "regular",
      "last_poster_username": "Threctory",
      "category_id": 5,
      "pinned_globally": false,
      "tags": null,
      "posters": [{
        "extras": null,
        "description": "Original Poster",
        "user_id": 2
      }, {
        "extras": null,
        "description": "Frequent Poster",
        "user_id": 7
      }, {
        "extras": null,
        "description": "Frequent Poster",
        "user_id": 13
      }, {
        "extras": null,
        "description": "Frequent Poster",
        "user_id": 14
      }, {
        "extras": "latest",
        "description": "Most Recent Poster",
        "user_id": 8
      }]
    }, {
      "id": 317,
      "title": "Zombi/ZombiU",
      "fancy_title": "Zombi/ZombiU",
      "slug": "zombi-zombiu",
      "posts_count": 2,
      "reply_count": 0,
      "highest_post_number": 2,
      "image_url": "http://static.giantbomb.com/uploads/scale_small/8/82063/2553376-zombiuclean.jpg",
      "created_at": "2015-08-17T13:53:00.382Z",
      "last_posted_at": "2015-08-17T18:11:30.465Z",
      "bumped": true,
      "bumped_at": "2015-08-17T18:11:30.465Z",
      "unseen": false,
      "last_read_post_number": 2,
      "unread": 0,
      "new_posts": 0,
      "pinned": false,
      "unpinned": null,
      "visible": true,
      "closed": false,
      "archived": false,
      "notification_level": 3,
      "bookmarked": false,
      "liked": false,
      "views": 17,
      "like_count": 0,
      "has_summary": false,
      "archetype": "regular",
      "last_poster_username": "ChristopheLeFou",
      "category_id": 5,
      "pinned_globally": false,
      "tags": null,
      "posters": [{
        "extras": null,
        "description": "Original Poster",
        "user_id": 1
      }, {
        "extras": "latest",
        "description": "Most Recent Poster",
        "user_id": 17
      }]
    }, {
      "id": 76,
      "title": "Batman: Arkham Knight",
      "fancy_title": "Batman: Arkham Knight",
      "slug": "batman-arkham-knight",
      "posts_count": 65,
      "reply_count": 18,
      "highest_post_number": 65,
      "image_url": "http://static.giantbomb.com/uploads/scale_small/8/82063/2606852-keyfull+9237457203.jpg",
      "created_at": "2015-04-27T13:26:37.347Z",
      "last_posted_at": "2015-08-17T16:01:46.960Z",
      "bumped": true,
      "bumped_at": "2015-08-17T16:01:46.960Z",
      "unseen": false,
      "last_read_post_number": 65,
      "unread": 0,
      "new_posts": 0,
      "pinned": false,
      "unpinned": null,
      "visible": true,
      "closed": false,
      "archived": false,
      "notification_level": 3,
      "bookmarked": false,
      "liked": true,
      "views": 422,
      "like_count": 7,
      "has_summary": true,
      "archetype": "regular",
      "last_poster_username": "DarthSmurfX",
      "category_id": 5,
      "pinned_globally": false,
      "tags": null,
      "posters": [{
        "extras": null,
        "description": "Original Poster",
        "user_id": 1
      }, {
        "extras": null,
        "description": "Frequent Poster",
        "user_id": 8
      }, {
        "extras": null,
        "description": "Frequent Poster",
        "user_id": 17
      }, {
        "extras": null,
        "description": "Frequent Poster",
        "user_id": 7
      }, {
        "extras": "latest",
        "description": "Most Recent Poster",
        "user_id": 13
      }]
    }, {
      "id": 130,
      "title": "The Witcher 3: Wild Hunt",
      "fancy_title": "The Witcher 3: Wild Hunt",
      "slug": "the-witcher-3-wild-hunt",
      "posts_count": 22,
      "reply_count": 6,
      "highest_post_number": 22,
      "image_url": "http://static.giantbomb.com/uploads/scale_small/0/3699/2698809-the+witcher+3+-+wild+hunt+v7.jpg",
      "created_at": "2015-05-06T15:09:23.430Z",
      "last_posted_at": "2015-08-14T15:03:54.472Z",
      "bumped": true,
      "bumped_at": "2015-08-14T15:03:54.472Z",
      "unseen": false,
      "last_read_post_number": 22,
      "unread": 0,
      "new_posts": 0,
      "pinned": false,
      "unpinned": null,
      "visible": true,
      "closed": false,
      "archived": false,
      "notification_level": 3,
      "bookmarked": false,
      "liked": false,
      "views": 236,
      "like_count": 2,
      "has_summary": false,
      "archetype": "regular",
      "last_poster_username": "Rewfus",
      "category_id": 5,
      "pinned_globally": false,
      "tags": null,
      "posters": [{
        "extras": "latest",
        "description": "Original Poster, Most Recent Poster",
        "user_id": 1
      }, {
        "extras": null,
        "description": "Frequent Poster",
        "user_id": 4
      }, {
        "extras": null,
        "description": "Frequent Poster",
        "user_id": 17
      }, {
        "extras": null,
        "description": "Frequent Poster",
        "user_id": 8
      }]
    }]
  }
}
